Metadata-Version: 1.0
Name: PRAF
Version: 1.3
Summary: Python framework for REST API
Home-page: https://github.com/boblefrag/python-rest-api-framework
Author: Yohann Gabory
Author-email: yohann@gabory.fr
License: UNKNOWN
Platform: UNKNOWN
